LICENSE.md
MANIFEST.in
README.md
README.rst
setup.py
deepvoice3_pytorch/__init__.py
deepvoice3_pytorch/builder.py
deepvoice3_pytorch/conv.py
deepvoice3_pytorch/deepvoice3.py
deepvoice3_pytorch/modules.py
deepvoice3_pytorch/nyanko.py
deepvoice3_pytorch/version.py
deepvoice3_pytorch.egg-info/PKG-INFO
deepvoice3_pytorch.egg-info/SOURCES.txt
deepvoice3_pytorch.egg-info/dependency_links.txt
deepvoice3_pytorch.egg-info/requires.txt
deepvoice3_pytorch.egg-info/top_level.txt
deepvoice3_pytorch/frontend/__init__.py
deepvoice3_pytorch/frontend/en/__init__.py
deepvoice3_pytorch/frontend/es/__init__.py
deepvoice3_pytorch/frontend/jp/__init__.py
deepvoice3_pytorch/frontend/ko/__init__.py
deepvoice3_pytorch/frontend/text/__init__.py
deepvoice3_pytorch/frontend/text/cleaners.py
deepvoice3_pytorch/frontend/text/cmudict.py
deepvoice3_pytorch/frontend/text/numbers.py
deepvoice3_pytorch/frontend/text/symbols.py