Metadata-Version: 2.1
Name: deepvoice3-pytorch
Version: 0.1.0
Summary: PyTorch implementation of convolutional networks-based text-to-speech synthesis models.
Home-page: UNKNOWN
License: UNKNOWN
Platform: UNKNOWN
Provides-Extra: bin
Provides-Extra: test
Provides-Extra: jp
